inaSpeechSegmenter/__init__.py
inaSpeechSegmenter/_version.py
inaSpeechSegmenter/export_funcs.py
inaSpeechSegmenter/features_vbx.py
inaSpeechSegmenter/io.py
inaSpeechSegmenter/pyannote_viterbi.py
inaSpeechSegmenter/remote_utils.py
inaSpeechSegmenter/resnet.py
inaSpeechSegmenter/segmenter.py
inaSpeechSegmenter/sidekit_mfcc.py
inaSpeechSegmenter/thread_returning.py
inaSpeechSegmenter/vbx_segmenter.py
inaSpeechSegmenter/viterbi_utils.py
inaspeechsegmenter-0.8.0.data/data/LICENSE
inaspeechsegmenter-0.8.0.data/scripts/ina_speech_segmenter.py
inaspeechsegmenter-0.8.0.data/scripts/ina_speech_segmenter_pyro_client.py
inaspeechsegmenter-0.8.0.data/scripts/ina_speech_segmenter_pyro_client_setjobs.py
inaspeechsegmenter-0.8.0.data/scripts/ina_speech_segmenter_pyro_server.py
inaspeechsegmenter-0.8.0.dist-info/LICENSE
inaspeechsegmenter-0.8.0.dist-info/METADATA
inaspeechsegmenter-0.8.0.dist-info/WHEEL
inaspeechsegmenter-0.8.0.dist-info/top_level.txt
inaspeechsegmenter-0.8.0.dist-info/RECORD
