Metadata-Version: 2.1
Name: inaSpeechSegmenter
Version: 0.8.0
Summary: CNN-based audio segmentation toolkit. Does voice activity detection, speech detection, music detection, noise detection, speaker gender recognition.
Home-page: https://github.com/ina-foss/inaSpeechSegmenter
Author: David Doukhan
Author-email: david.doukhan@gmail.com
License: MIT
Keywords: speech-segmentation,audio-analysis,music-detection,noise-detection,speech-detection,speech-music,gender-classification,gender-representation,speaker-gender,speech,music,noise,gender,voice-activity-detection,speech-activity-detection,VAD,praat
Classifier: Development Status :: 4 - Beta
Classifier: Intended Audience :: Developers
Classifier: Intended Audience :: Education
Classifier: Intended Audience :: Science/Research
Classifier: License :: OSI Approved :: MIT License
Classifier: Operating System :: OS Independent
Classifier: Programming Language :: Python :: 3
Classifier: Programming Language :: Python :: 3 :: Only
Classifier: Programming Language :: Python :: 3.8
Classifier: Programming Language :: Python :: 3.9
Classifier: Programming Language :: Python :: 3.10
Classifier: Programming Language :: Python :: 3.11
Classifier: Programming Language :: Python :: 3.12
Classifier: Programming Language :: Python :: 3.13
Classifier: Topic :: Multimedia :: Sound/Audio
Classifier: Topic :: Multimedia :: Sound/Audio :: Analysis
Classifier: Topic :: Multimedia :: Sound/Audio :: Speech
Classifier: Topic :: Scientific/Engineering
Classifier: Topic :: Scientific/Engineering :: Artificial Intelligence
Classifier: Topic :: Software Development
Classifier: Topic :: Software Development :: Libraries
Classifier: Topic :: Software Development :: Libraries :: Python Modules
Classifier: Topic :: Sociology
Requires-Python: >=3.8
License-File: LICENSE
Requires-Dist: numpy
Requires-Dist: pandas
Requires-Dist: scikit-image
Requires-Dist: pyannote.core
Requires-Dist: matplotlib
Requires-Dist: Pyro4
Requires-Dist: pytextgrid
Requires-Dist: soundfile
Requires-Dist: tensorflow[and-cuda]
Requires-Dist: onnxruntime-gpu
